tdxlib/__init__.py
tdxlib/tdx_api_exceptions.py
tdxlib/tdx_asset_integration.py
tdxlib/tdx_client_portal_integration.py
tdxlib/tdx_config.py
tdxlib/tdx_constants.py
tdxlib/tdx_integration.py
tdxlib/tdx_report.py
tdxlib/tdx_report_integration.py
tdxlib/tdx_ticket.py
tdxlib/tdx_ticket_attribs.py
tdxlib/tdx_ticket_integration.py
tdxlib/tdx_utils.py
tdxlib-0.6.1.dist-info/licenses/LICENSE
tdxlib-0.6.1.dist-info/METADATA
tdxlib-0.6.1.dist-info/WHEEL
tdxlib-0.6.1.dist-info/top_level.txt
tdxlib-0.6.1.dist-info/RECORD
