Metadata-Version: 2.4
Name: TDXLib
Version: 0.6.1
Summary: a python library for interacting with the TeamDynamix Web API
Home-page: https://github.com/cedarville-university/tdxlib
Author: Nat Biggs, Stephen Gaines, Josiah Lansford
Author-email: tdxlib@cedarville.edu
License: GNU General Public License v3.0
Requires-Python: >=3.6
License-File: LICENSE
Requires-Dist: python-dateutil
Requires-Dist: requests
Requires-Dist: PYjwt
Requires-Dist: typing-extensions
Dynamic: author
Dynamic: author-email
Dynamic: description
Dynamic: description-content-type
Dynamic: home-page
Dynamic: license
Dynamic: license-file
Dynamic: requires-dist
Dynamic: requires-python
Dynamic: summary
